krakenpull/__init__.py
krakenpull/client.py
krakenpull/data.py
krakenpull/env.py
krakenpull/models.py
krakenpull/utils.py
krakenpull-3.0.0.dist-info/METADATA
krakenpull-3.0.0.dist-info/WHEEL
krakenpull-3.0.0.dist-info/RECORD
