Metadata-Version: 2.1
Name: krakenpull
Version: 3.0.0
Summary: A user friendly Kraken API client using pydantic 🐙
Author: marc
Author-email: marc@mawaie.com
Requires-Python: >=3.9,<4.0
Classifier: Programming Language :: Python :: 3
Classifier: Programming Language :: Python :: 3.9
Classifier: Programming Language :: Python :: 3.10
Classifier: Programming Language :: Python :: 3.11
Requires-Dist: pydantic (>=2.7.0,<3.0.0)
Requires-Dist: requests (>=2.31.0,<3.0.0)
